setup.py
cratis_admin/__init__.py
cratis_admin/features.py
django_cratis_admin.egg-info/PKG-INFO
django_cratis_admin.egg-info/SOURCES.txt
django_cratis_admin.egg-info/dependency_links.txt
django_cratis_admin.egg-info/requires.txt
django_cratis_admin.egg-info/top_level.txt